kyujipy/__init__.py
kyujipy/basic_converter.py
kyujipy/data/kakikae_simplified.cson
kyujipy/data/kakikae_variants.cson
kyujipy/data/kyujitai_simplified.cson
kyujipy/data/kyujitai_variants.cson
kyujipy/export_to_json.py
kyujipy/kyujitai_converter.py
kyujipy-0.6.7.dist-info/LICENSE
kyujipy-0.6.7.dist-info/METADATA
kyujipy-0.6.7.dist-info/WHEEL
kyujipy-0.6.7.dist-info/RECORD
