Metadata-Version: 2.3
Name: kyujipy
Version: 0.6.7
Summary: A Python library to convert Japanese texts from Shinjitai to Kyujitai and vice versa
Home-page: https://github.com/DrTurnon/kyujipy
License: MIT
Author: Emmanuel Ternon
Author-email: emmanuel.ternon@outlook.com
Requires-Python: >=3.11,<4.0
Classifier: License :: OSI Approved :: MIT License
Classifier: Programming Language :: Python :: 3
Classifier: Programming Language :: Python :: 3.11
Classifier: Programming Language :: Python :: 3.12
Classifier: Programming Language :: Python :: 3.13
Requires-Dist: build (>=1.2.2.post1,<2.0.0)
Requires-Dist: cson (>=0.8,<0.9)
Project-URL: Repository, https://github.com/DrTurnon/kyujipy
